spatial_utils/__init__.py
spatial_utils/_version.py
spatial_utils/io/__init__.py
spatial_utils/io/visium.py
spatial_utils/io/_tests/__init__.py
spatial_utils/io/_tests/test_visium_io.py
spatial_utils-0.0.1.dist-info/LICENSE
spatial_utils-0.0.1.dist-info/METADATA
spatial_utils-0.0.1.dist-info/WHEEL
spatial_utils-0.0.1.dist-info/top_level.txt
spatial_utils-0.0.1.dist-info/RECORD
