Metadata-Version: 2.1
Name: spatial-utils
Version: 0.0.1
Summary: a collection of utilities for spatial-omics analysis
Home-page: https://github.com/kevinyamauchi/spatial-utils
Author: Kevin Yamauchi
Author-email: kevin.yamauchi@gmail.com
License: BSD-3
Platform: UNKNOWN
Classifier: Development Status :: 4 - Beta
Classifier: Intended Audience :: Developers
Classifier: Topic :: Software Development :: Testing
Classifier: Programming Language :: Python
Classifier: Programming Language :: Python :: 3
Classifier: Programming Language :: Python :: 3.7
Classifier: Programming Language :: Python :: 3.8
Classifier: Programming Language :: Python :: 3.9
Classifier: Operating System :: OS Independent
Classifier: License :: OSI Approved :: BSD License
Requires-Python: >=3.7
Requires-Dist: numpy
Requires-Dist: notebook
Requires-Dist: scipy
Requires-Dist: squidpy[all]
